Metadata-Version: 2.1
Name: npview
Version: 0.0.5
Summary: CLI utility for previewing .npy files
Home-page: https://github.com/a-r-j/npview
Author: Arian Jamasb
Author-email: arian@jamasb.io
License: MIT License
Project-URL: Bug Reports, https://github.com/a-r-j/npview/issues
Project-URL: Source, https://github.com/a-r-j/npview
Keywords: numpy data .npy
Platform: UNKNOWN
Classifier: Development Status :: 5 - Production/Stable
Classifier: Intended Audience :: Science/Research
Classifier: Topic :: Scientific/Engineering
Classifier: Topic :: Scientific/Engineering :: Chemistry
Classifier: Topic :: Scientific/Engineering :: Bio-Informatics
Classifier: License :: OSI Approved :: MIT License
Classifier: Programming Language :: Python :: 2
Classifier: Programming Language :: Python :: 2.7
Classifier: Programming Language :: Python :: 3
Classifier: Programming Language :: Python :: 3.6
Classifier: Programming Language :: Python :: 3.7
Classifier: Programming Language :: Python :: 3.8
Classifier: Programming Language :: Python :: 3.9
License-File: LICENSE
